Workbook

Sheet Базовый
A1: Участок линии | B1: Статус подбора из БД | C1: Единица промышленного оборудования | D1: Комплектующие | E1: Количество единиц | F1: Количество комплектующих | G1: ед.изм. | H1: Общее количество в единице пром оборудования | I1: Себестоимость комплектующих, с НДС | J1: Стоимость комплектующих в единице пром оборудования, с НДС | K1: Накрутка | L1: Цена выходная | M1: тип | P1: Тип накрутки | Q1: Процент накрутки | S1: себестоимость | T1: Цена | U1: Маржа
A2: Участок линии | C2: Единица промышленного оборудования | D2: Металлоконструкции | E2: 0 | F2: 0 | G2: кг. | H2: =E2*F2 -> 0 | I2: 0 | J2: =I2*H2 -> 0 | K2: =IF(M2="товар",$Q$4, IF(M2="м/к",$Q$2,IF(M2="комп",$Q$3,IF(M2="услуга",$Q$5,0)))) -> 1 | L2: =(1+K2)*J2 -> 0 | M2: м/к | P2: м/к | Q2: 1 | S2: =SUM(J:J) -> 0 | T2: =SUM(L:L) -> 0 | U2: =T2-S2 -> 0
A3: Участок линии | C3: Единица промышленного оборудования | D3: Токарка/фрезеровка | E3: 0 | F3: 0 | G3: кг. | H3: =E3*F3 -> 0 | I3: 0 | J3: =I3*H3 -> 0 | K3: =IF(M3="товар",$Q$4, IF(M3="м/к",$Q$2,IF(M3="комп",$Q$3,IF(M3="услуга",$Q$5,0)))) -> 1 | L3: =(1+K3)*J3 -> 0 | M3: м/к | P3: комп | Q3: 0.5 | U3: =U2/T2 -> #DIV/0!
A4: Участок линии | C4: Единица промышленного оборудования | D4: Комплектующие | E4: 0 | F4: 0 | G4: шт. | H4: =E4*F4 -> 0 | I4: 0 | J4: =I4*H4 -> 0 | K4: =IF(M4="товар",$Q$4, IF(M4="м/к",$Q$2,IF(M4="комп",$Q$3,IF(M4="услуга",$Q$5,0)))) -> 0.5 | L4: =(1+K4)*J4 -> 0 | M4: комп | P4: товар | Q4: 0.3 | S4: Удельная маржа | U4: =(U2/1.2)/(Базовый!T5/22) -> #DIV/0!
A5: Участок линии | C5: Единица промышленного оборудования | D5: Товар | E5: 0 | F5: 0 | G5: шт. | H5: =E5*F5 -> 0 | I5: 0 | J5: =I5*H5 -> 0 | K5: =IF(M5="товар",$Q$4, IF(M5="м/к",$Q$2,IF(M5="комп",$Q$3,IF(M5="услуга",$Q$5,0)))) -> 0.3 | L5: =(1+K5)*J5 -> 0 | M5: товар | P5: услуга | Q5: 0.1 | S5: трудозатарты | T5: =SUMIF(G:G,"смен",H:H) -> 0 | U5: смен
A6: Участок линии | C6: Единица промышленного оборудования | D6: Услуга | E6: 0 | F6: 0 | G6: смен | H6: =E6*F6 -> 0 | I6: 0 | J6: =I6*H6 -> 0 | K6: =IF(M6="товар",$Q$4, IF(M6="м/к",$Q$2,IF(M6="комп",$Q$3,IF(M6="услуга",$Q$5,0)))) -> 0.1 | L6: =(1+K6)*J6 -> 0 | M6: услуга
H7: =E7*F7 -> 0 | J7: =I7*H7 -> 0 | K7: =IF(M7="товар",$Q$4, IF(M7="м/к",$Q$2,IF(M7="комп",$Q$3,IF(M7="услуга",$Q$5,0)))) -> 0 | L7: =(1+K7)*J7 -> 0
H8: =E8*F8 -> 0 | J8: =I8*H8 -> 0 | K8: =IF(M8="товар",$Q$4, IF(M8="м/к",$Q$2,IF(M8="комп",$Q$3,IF(M8="услуга",$Q$5,0)))) -> 0 | L8: =(1+K8)*J8 -> 0
H9: =E9*F9 -> 0 | J9: =I9*H9 -> 0 | K9: =IF(M9="товар",$Q$4, IF(M9="м/к",$Q$2,IF(M9="комп",$Q$3,IF(M9="услуга",$Q$5,0)))) -> 0 | L9: =(1+K9)*J9 -> 0
H10: =E10*F10 -> 0 | J10: =I10*H10 -> 0 | K10: =IF(M10="товар",$Q$4, IF(M10="м/к",$Q$2,IF(M10="комп",$Q$3,IF(M10="услуга",$Q$5,0)))) -> 0 | L10: =(1+K10)*J10 -> 0
H11: =E11*F11 -> 0 | J11: =I11*H11 -> 0 | K11: =IF(M11="товар",$Q$4, IF(M11="м/к",$Q$2,IF(M11="комп",$Q$3,IF(M11="услуга",$Q$5,0)))) -> 0 | L11: =(1+K11)*J11 -> 0
H12: =E12*F12 -> 0 | J12: =I12*H12 -> 0 | K12: =IF(M12="товар",$Q$4, IF(M12="м/к",$Q$2,IF(M12="комп",$Q$3,IF(M12="услуга",$Q$5,0)))) -> 0 | L12: =(1+K12)*J12 -> 0
H13: =E13*F13 -> 0 | J13: =I13*H13 -> 0 | K13: =IF(M13="товар",$Q$4, IF(M13="м/к",$Q$2,IF(M13="комп",$Q$3,IF(M13="услуга",$Q$5,0)))) -> 0 | L13: =(1+K13)*J13 -> 0
H14: =E14*F14 -> 0 | J14: =I14*H14 -> 0 | K14: =IF(M14="товар",$Q$4, IF(M14="м/к",$Q$2,IF(M14="комп",$Q$3,IF(M14="услуга",$Q$5,0)))) -> 0 | L14: =(1+K14)*J14 -> 0
H15: =E15*F15 -> 0 | J15: =I15*H15 -> 0 | K15: =IF(M15="товар",$Q$4, IF(M15="м/к",$Q$2,IF(M15="комп",$Q$3,IF(M15="услуга",$Q$5,0)))) -> 0 | L15: =(1+K15)*J15 -> 0
H16: =E16*F16 -> 0 | J16: =I16*H16 -> 0 | K16: =IF(M16="товар",$Q$4, IF(M16="м/к",$Q$2,IF(M16="комп",$Q$3,IF(M16="услуга",$Q$5,0)))) -> 0 | L16: =(1+K16)*J16 -> 0
H17: =E17*F17 -> 0 | J17: =I17*H17 -> 0 | K17: =IF(M17="товар",$Q$4, IF(M17="м/к",$Q$2,IF(M17="комп",$Q$3,IF(M17="услуга",$Q$5,0)))) -> 0 | L17: =(1+K17)*J17 -> 0
H18: =E18*F18 -> 0 | J18: =I18*H18 -> 0 | K18: =IF(M18="товар",$Q$4, IF(M18="м/к",$Q$2,IF(M18="комп",$Q$3,IF(M18="услуга",$Q$5,0)))) -> 0 | L18: =(1+K18)*J18 -> 0
... H1000: =E1000*F1000 -> 0 | J1000: =I1000*H1000 -> 0 | K1000: =IF(M1000="товар",$Q$4, IF(M1000="м/к",$Q$2,IF(M1000="комп",$Q$3,IF(M1000="услуга",$Q$5,0)))) -> 0 | L1000: =(1+K1000)*J1000 -> 0

Sheet анализ стоимости
A2: срок простоя от поставки/изготовления | B2: 1 | C2: мес
A3: Сотрудников в проекте | B3: 6 | C3: чел
A4: срок выполнения работ | B4: =Базовый!T5/(22*B3)+B2 -> 1 | C4: мес
A5: маржа без НДС | B5: =Базовый!U2/1000 / 1.2 -> 0 | C5: тыс. руб.
A6: Удельная маржа | B6: =B5/(Базовый!T5/22) -> #DIV/0! | C6: тыс. руб.
A11: блок | B11: доля цены
A12: м/к | B12: =SUMIF(Базовый!M:M,'анализ стоимости'!A12,Базовый!L:L)/SUM(Базовый!L:L) -> #DIV/0!
A13: комп | B13: =SUMIF(Базовый!M:M,'анализ стоимости'!A13,Базовый!L:L)/SUM(Базовый!L:L) -> #DIV/0!
A14: товар | B14: =SUMIF(Базовый!M:M,'анализ стоимости'!A14,Базовый!L:L)/SUM(Базовый!L:L) -> #DIV/0!
A15: услуга | B15: =SUMIF(Базовый!M:M,'анализ стоимости'!A15,Базовый!L:L)/SUM(Базовый!L:L) -> #DIV/0!

Sheet META
A1: template_version | B1: created_date | C1: created_by | D1: comment
A2: V1.0 | B2: 46052
